<?xml version="1.0" encoding="UTF-8"?><date>26/04/2022</date><accountFrom>Ben B</accountFrom><accountTo>Jon A</accountTo><narrative>Coffee</narrative><amount>4.86</amount><date>26/04/2022</date><accountFrom>Stephen S</accountFrom><accountTo>Ben B</accountTo><narrative>Services Rendered</narrative><amount>1.92</amount><date>26/04/2022</date><accountFrom>Ben B</accountFrom><accountTo>Chris W</accountTo><narrative>Misc Morale</narrative><amount>5.76</amount><date>26/04/2022</date><accountFrom>Ben B</accountFrom><accountTo>Sarah T</accountTo><narrative>Pokemon Training</narrative><amount>6.2</amount><date>26/04/2022</date><accountFrom>Ben B</accountFrom><accountTo>Stephen S</accountTo><narrative>Sandbox Help</narrative><amount>6.36</amount><date>26/04/2022</date><accountFrom>Gergana I</accountFrom><accountTo>Ben B</accountTo><narrative>Lunch</narrative><amount>9.07</amount><date>26/04/2022</date><accountFrom>Ben B</accountFrom><accountTo>Tim L</accountTo><narrative>Fantasy Football</narrative><amount>1.15</amount><date>26/04/2022</date><accountFrom>Ben B</accountFrom><accountTo>Chris W</accountTo><narrative>Rails Consultancy</narrative><amount>9.91</amount><date>26/04/2022</date><accountFrom>Ben B</accountFrom><accountTo>Dan W</accountTo><narrative>Git-Fu Rendered</narrative><amount>9.85</amount><date>26/04/2022</date><accountFrom>Sarah T</accountFrom><accountTo>Ben B</accountTo><narrative>Beers</narrative><amount>0.51</amount><date>26/04/2022</date><accountFrom>Todd</accountFrom><accountTo>Ben B</accountTo><narrative>Coffee</narrative><amount>11.07</amount><date>26/04/2022</date><accountFrom>Ben B</accountFrom><accountTo>Dan W</accountTo><narrative>Rails Consultancy</narrative><amount>9.96</amount><date>26/04/2022</date><accountFrom>Stephen S</accountFrom><accountTo>Ben B</accountTo><narrative>Audit and Other Financial Services</narrative><amount>1.51</amount><date>26/04/2022</date><accountFrom>Todd</accountFrom><accountTo>Ben B</accountTo><narrative>Golf Bets</narrative><amount>11.83</amount><date>26/04/2022</date><accountFrom>Jon A</accountFrom><accountTo>Ben B</accountTo><narrative>Sandcastle Help</narrative><amount>6.75</amount><date>26/04/2022</date><accountFrom>Ben B</accountFrom><accountTo>Sarah T</accountTo><narrative>Poker Winnings</narrative><amount>5.15</amount><date>26/04/2022</date><accountFrom>Ben B</accountFrom><accountTo>Dan W</accountTo><narrative>Misc Morale</narrative><amount>9.24</amount><date>26/04/2022</date><accountFrom>Chris W</accountFrom><accountTo>Ben B</accountTo><narrative>Beers</narrative><amount>10.41</amount><date>26/04/2022</date><accountFrom>Ben B</accountFrom><accountTo>Tim L</accountTo><narrative>Coffee</narrative><amount>4.29</amount><date>26/04/2022</date><accountFrom>Ben B</accountFrom><accountTo>Todd</accountTo><narrative>Beers</narrative><amount>0.69</amount><date>26/04/2022</date><accountFrom>Ben B</accountFrom><accountTo>Todd</accountTo><narrative>Lunch</narrative><amount>11.18</amount><date>26/04/2022</date><accountFrom>Gergana I</accountFrom><accountTo>Ben B</accountTo><narrative>Misc Morale</narrative><amount>10.91</amount><date>26/04/2022</date><accountFrom>Chris W</accountFrom><accountTo>Ben B</accountTo><narrative>Coffee</narrative><amount>9.48</amount><date>26/04/2022</date><accountFrom>Tim L</accountFrom><accountTo>Ben B</accountTo><narrative>Misc Morale</narrative><amount>8.68</amount><date>26/04/2022</date><accountFrom>Ben B</accountFrom><accountTo>Gergana I</accountTo><narrative>Beers</narrative><amount>5.52</amount><date>26/04/2022</date><accountFrom>Chris W</accountFrom><accountTo>Ben B</accountTo><narrative>Coffee</narrative><amount>5.96</amount><date>26/04/2022</date><accountFrom>Ben B</accountFrom><accountTo>Chris W</accountTo><narrative>Jenkins Fees</narrative><amount>7.78</amount><date>26/04/2022</date><accountFrom>Ben B</accountFrom><accountTo>Sarah T</accountTo><narrative>Lunch</narrative><amount>10.09</amount><date>26/04/2022</date><accountFrom>Ben B</accountFrom><accountTo>Todd</accountTo><narrative>Golf Bets</narrative><amount>2.15</amount><date>26/04/2022</date><accountFrom>Ben B</accountFrom><accountTo>Sam N</accountTo><narrative>Pokemon Training</narrative><amount>4.01</amount><date>26/04/2022</date><accountFrom>Ben B</accountFrom><accountTo>Sam N</accountTo><narrative>Coffee</narrative><amount>9</amount><date>26/04/2022</date><accountFrom>Sarah T</accountFrom><accountTo>Ben B</accountTo><narrative>Pokemon Training</narrative><amount>8.72</amount><date>26/04/2022</date><accountFrom>Todd</accountFrom><accountTo>Ben B</accountTo><narrative>Pokemon Training</narrative><amount>8.72</amount><date>26/04/2022</date><accountFrom>Ben B</accountFrom><accountTo>Rob S</accountTo><narrative>Snooker Night</narrative><amount>10.14</amount>